thin_osm_api_wrapper/__init__.py
thin_osm_api_wrapper/api.py
thin_osm_api_wrapper-0.0.5.dist-info/licenses/LICENSE
thin_osm_api_wrapper-0.0.5.dist-info/METADATA
thin_osm_api_wrapper-0.0.5.dist-info/WHEEL
thin_osm_api_wrapper-0.0.5.dist-info/top_level.txt
thin_osm_api_wrapper-0.0.5.dist-info/RECORD
