Metadata-Version: 2.4
Name: thin_osm_api_wrapper
Version: 0.0.5
Summary: thin wrapper of https://wiki.openstreetmap.org/wiki/API
Home-page: https://github.com/matkoniecz/thin_osm_api_python_wrapper
Author: Mateusz Konieczny
Classifier: Programming Language :: Python :: 3
Classifier: License :: OSI Approved :: MIT License
Classifier: Operating System :: OS Independent
License-File: LICENSE
Dynamic: author
Dynamic: classifier
Dynamic: description
Dynamic: description-content-type
Dynamic: home-page
Dynamic: license-file
Dynamic: summary
